node_chunker/__init__.py
node_chunker/chunks.py
node_chunker/document_chunking.py
node_chunker/docx_chunking.py
node_chunker/html_chunking.py
node_chunker/jupyter_chunking.py
node_chunker/md_chunking.py
node_chunker/pdf_chunking.py
node_chunker/rst_chunking.py
node_chunker/utils.py
node_chunker-0.1.2.dist-info/METADATA
node_chunker-0.1.2.dist-info/WHEEL
node_chunker-0.1.2.dist-info/licenses/LICENSE
node_chunker-0.1.2.dist-info/RECORD
