Metadata-Version: 2.4
Name: node-chunker
Version: 0.1.2
Summary: A Python package for Document Node Chunking based on Table of Contents
Project-URL: Homepage, https://github.com/KameniAlexNea/llama-index-toc-parser
Project-URL: Repository, https://github.com/KameniAlexNea/llama-index-toc-parser
Project-URL: Bug Tracker, https://github.com/KameniAlexNea/llama-index-toc-parser/issues
Author-email: Alex Kameni <kamenialexnea@gmail.com>
License: MIT
License-File: LICENSE
Keywords: LLM,NLP,RAG,TOC,chunking,document,llama-index,parser
Classifier: Intended Audience :: Education
Classifier: License :: OSI Approved :: MIT License
Classifier: Operating System :: OS Independent
Classifier: Programming Language :: Python :: 3
Classifier: Programming Language :: Python :: 3.10
Classifier: Programming Language :: Python :: 3.11
Classifier: Topic :: Education
Classifier: Topic :: Scientific/Engineering :: Artificial Intelligence
Classifier: Topic :: Software Development :: Libraries :: Python Modules
Classifier: Topic :: Text Processing :: Markup
Requires-Python: <4.0,>=3.10
Requires-Dist: llama-index-core<0.13,>=0.12.36
Requires-Dist: markitdown[docx,pdf]>=0.1.1
Requires-Dist: pymupdf>=1.25.5
Requires-Dist: requests
Provides-Extra: dev
Requires-Dist: black<25.0,>=23.0; extra == 'dev'
Requires-Dist: build; extra == 'dev'
Requires-Dist: codespell>=2.2.0; extra == 'dev'
Requires-Dist: coverage>=5.0; extra == 'dev'
Requires-Dist: mypy>=1.0; extra == 'dev'
Requires-Dist: pickleshare; extra == 'dev'
Requires-Dist: pre-commit>=3.0; extra == 'dev'
Requires-Dist: pylint<4.0,>=2.15; extra == 'dev'
Requires-Dist: ruff>=0.1.0; extra == 'dev'
Requires-Dist: safety; extra == 'dev'
Requires-Dist: sphinx; extra == 'dev'
Requires-Dist: tox; extra == 'dev'
Requires-Dist: twine; extra == 'dev'
Requires-Dist: wheel; extra == 'dev'
Provides-Extra: test
Requires-Dist: coverage>=5.0; extra == 'test'
